{
"2BK0kX": "Maoni 1",
"1iTQWW": "1 ameipenda",
"1zFZRi": "Rafiki 1 Mnayeheshimiana",
"dOvSd": "Sekunde chache zilizopita",
"GNe14": "asubuhi",
"1Mp78k": "Apr",
"4AgfD3": "Aprili",
"1r1h2U": "Agosti",
"RJ3VL": "Ongeza Picha ya Jalada",
"4aWyhh": "Aprili",
"45DS2A": "Ago",
"3T8u8I": "Agosti",
"qYo3D": "Rudi",
"eUsF0": "Siwezi Kwenda",
"27z3od": "Katisha",
"2qMcb7": "Batilisha",
"1Ap2bU": "Batilisha",
"4gzSLh": "Ghairi",
"3tsppz": "Batilisha",
"2izdvt": "Ghairi",
"11HeEl": "Ghairi ombi la kujiunga",
"2onE3q": "Chagua Picha",
"3dqBmW": "Chagua ni machapisho ya nani ambayo hutaki kuyakosa. Utayapata kila wakati juu ya Taarifa yako.",
"tnj8J": "Funga",
"1W4wkF": "Kikundi kilichofungwa",
"32a2Ks": "Toa maoni",
"2OG1Fe": "Thibitisha",
"3jpqKo": "Thibitisha",
"2Qj5io": "Unda",
"1kJQDA": "Dis",
"1oXBuK": "Disemba",
"4flSxN": "Siku:",
"446633": "Dis",
"3vS0xI": "Disemba",
"2jWRjI": "Futa",
"1Nhz98": "Futa",
"476OR1": "Futa",
"1LoscC": "Futa Maoni",
"1Mqevn": "Futa Maoni",
"l9YPL": "Futa Chapisho",
"254HpQ": "Gundua Kurasa ambazo zinalingana na mapendeleo yako",
"2u8AS3": "Imekamilika",
"pLWAV": "Hariri Maoni",
"rlxJm": "Hariri Ujumbe",
"1l6E3p": "Imehaririwa",
"3afZk4": "Imehaririwa",
"3svPFF": "Tukio la {name}",
"1mFzFq": "Feb",
"2tPyCj": "Februari",
"26bAU5": "BILA MALIPO",
"4rTcAz": "Februari",
"25HE3M": "Anaowafuata",
"3NRDAr": "Iju",
"1ycHPR": "Ijumaa",
"2R2Arn": "Pata Fahamisho",
"e5TWi": "Nahudhuria",
"1hvHnO": "Puuza",
"3LwXZw": "Alika Marafiki",
"3y4HCn": "Jan",
"46YziU": "Januari",
"1xUphJ": "Jul",
"1aRhAh": "Julai",
"2eRp8": "Jun",
"CA2HP": "Juni",
"3qJBMW": "Januari",
"1ykxF0": "Jiunge na Kikundi",
"4ArtBd": "Julai",
"TPzvS": "Juni",
"3NA4qF": "Jifunze Zaidi.",
"1Tyz2A": "Poa",
"23Dtnu": "Poa",
"2WJJRI": "Machi",
"EdNF8": "Mei",
"2Or3o0": "Mei",
"4hMTjQ": "Machi(3)",
"2CpxDl": "Machi",
"4wGzil": "Mei",
"1UWcqT": "Mei",
"1TVcbh": "Labda",
"37YAX8": "Wanachama",
"2bD1FC": "Jumatatu",
"2FOfez": "Jumatatu",
"1BgnYW": "Mwezi:",
"453XAv": "Chaguo zaidi",
"oMdIM": "Nov",
"4rdPcX": "Novemba",
"1eNmiS": "Hapana",
"2SL0xS": "La",
"3hbuGm": "Hakuna Muunganisho wa Mtandao",
"O6o3r": "Novemba",
"3RPWWP": "Okt",
"1tdTJA": "Oktoba",
"1Qi1Im": "SAWA",
"2vgSEi": "SAWA",
"8M01o": "SAWA",
"4wLWq": "Vipachiko vya Awali",
"4qA6Cd": "Okt",
"2GOVo6": "Oktoba",
"13UWti": "Sawa",
"33LJbi": "Nyingine",
"fUew2": "mchana\/ jioni",
"I3gtR": "Iliyopita",
"QZ4x4": "Sitisha",
"4haKXk": "Watu Wanaopenda Hii",
"3Mf4uR": "Watu walioona hii",
"qa2Hm": "Picha",
"1I1E7p": "Picha",
"3Xwfky": "Bana Chapisho",
"2QAjpy": "Cheza",
"kQsg4": "Chakura",
"24g3JP": "Mdokoe pia",
"3EyLQ9": "Ungependa kuchakura {name}?",
"1VxjC7": "Chapisho",
"1ZPsTk": "Pachika",
"1cUS7r": "Weka ni nani utakayemwona kwanza",
"2IGrMf": "Panga Ni Nani Utamwona Kwanza",
"3Ukqpm": "Picha ya Wasifu",
"2dgDU6": "Unganika tena na Watu Uliokoma Kuwafuata",
"291FjF": "Unganisha tena na Watu Uliokoma Kuwafuata",
"1Yj34Y": "Jibu",
"255GWb": "Sep",
"1Ytv6r": "Septemba",
"1zT5n6": "Jumamosi",
"3rkYx4": "Jumamosi",
"3HxTS": "Tafuta marafiki wa kuchakura",
"3bFdK9": "Kundi la siri",
"3DQqyr": "Tazama Kwanza",
"2MJpbq": "Tazama Zaidi",
"2RdgLg": "Septemba",
"g7iOX": "Shiriki",
"2tOYdn": "Hitilafu Imetokea",
"4umoOR": "Imedhaminiwa",
"19jJmF": "Matukio Yaliyosajiliwa",
"2Xf3iY": "Chakura Zilizopendekezwa",
"4myjEh": "Jumapili",
"zyLEU": "Jumapili",
"19iskg": "Chukua usukani na ugeuze Taarifa zako kukufaa.",
"2Irzi3": "Gonga ili uchague ni machapisho ya nani unayotaka kukomesha kuona katika Taarifa zako. Ni wewe tu utakayejua.",
"r1481": "Alh",
"D0R1K": "Alhamisi",
"2W7SVp": "Leo",
"3xPNbR": "Jumanne",
"4nrOt7": "Jumanne",
"4dk3ae": "Acha kuwafuata Watu ili Ufiche Machapisho Yao",
"1IMZk3": "Usiwafuate watu ili ufiche machapisho yao",
"234vfq": "Kutofuata",
"Wfjjz": "Hainipendezi tena",
"WMtWe": "Ondoa Chapisho",
"3AmfBe": "Inayokuja",
"4njC7k": "Siku za Kuzaliwa Zijazo",
"1KMP4x": "Sasisha",
"1IuVOn": "Tazama Zaidi",
"4DtVZ5": "Tazama maoni ya awali",
"2ZAP4T": "Jumatano",
"3vfJHJ": "Jumatano",
"28uwj3": "Andika maoni...",
"23o9mz": "Mwaka:",
"3cS3Lj": "Ndiyo",
"3UynCW": "Ndiyo",
"4CBaGv": "Unachagua kukomesha kuona machapisho kutoka kwa watu hawa. Gonga ili uwafuate tena na uone machapisho yao katika Taarifa zako.",
"3ukPr0": "Umemchakura {name}!",
"15A5ct": "kama dakika moja iliyopita",
"1vcz2v": "asubuhi",
"49rsPR": "siku",
"32e9V9": "mwezi",
"3mUbF": "Ya",
"vnTRR": "Tarehe ishirini na mbili",
"3rgwql": "mchana\/ jioni",
"RYouN": "ya ama wa tatu",
"2OiJ84": "a  kwanza",
"rNBUl": "tarehe 21",
"1A1ADn": "Tarehe 31",
"2PDEw6": "siku ya 10",
"2UGg7U": "ya 11 or wa 11",
"9rKEZ": "Tarehe 12",
"3CEa1S": "Tarehe kumi na tatu",
"49cgef": "Ya",
"xwW5g": "siku ya",
"2SZRNm": "tarehe 16",
"2QPwjb": "Tarehe 17",
"2Bl9U9": "Tarehe 18",
"2Zoso8": "ya",
"1fRQcz": "Tarehe 20",
"2u4Jxm": "Tarehe 24",
"41pMxa": "ya",
"1g41ub": "Tarehe 26",
"154MOo": "Tarehe 27",
"drrwm": "ya\/wa\/za",
"2InA68": "Tarehe 30",
"4uKsGN": "Tarehe 4",
"301rsb": "Siku ya tano",
"3sySWz": "ya",
"39Q6dQ": "ya",
"4o0F4m": "Tarehe 8",
"3pRZOl": "Ya",
"zhzEQ": "mwaka",
"43got5": "Maoni {comment_count}",
"2SvDtw": "Watu {count} wanaenda",
"aT1np": "{date} saa {time}",
"2oPlum": "{day} saa {time}",
"4c6UVe": "{day} saa {time}",
"4EdPCY": "Marafiki {mutual_friend_count} mnaojuana",
"3J6srQ": "{name} hajajibu uchakuro wako wa mwisho.",
"2zU5EE": "{name} amekualika",
"gSIOP": "{name} anaenda",
"1xlsYK": "{name} anaweza kwenda",
"2stvx5": "Saa {num_hours} zilizopita",
"3Yigmx": "{num_likes_count} wamependezwa",
"304anR": "Dakika {num_minutes} zilizopita",
"1b0B8d": "{position} katika {employer}",
"__signature": "@generated SignedSource<<9fc51f8f52ddb0403d97ef4e9d771a57>>"
}